pfizer_stratus_swagger/__init__.py
pfizer_stratus_swagger/__main__.py
pfizer_stratus_swagger/read_template_yml.py
pfizer_stratus_swagger/run.py
pfizer_stratus_swagger-0.1.dist-info/LICENSE
pfizer_stratus_swagger-0.1.dist-info/METADATA
pfizer_stratus_swagger-0.1.dist-info/WHEEL
pfizer_stratus_swagger-0.1.dist-info/entry_points.txt
pfizer_stratus_swagger-0.1.dist-info/top_level.txt
pfizer_stratus_swagger-0.1.dist-info/RECORD
