Metadata-Version: 2.1
Name: pfizer-stratus-swagger
Version: 0.1
Summary: A Swagger generation from Stratus AWS Lambda applications
Home-page: https://github.com/piotrmaslanka/pfizer-stratus-swagger
Author: Piotr Maślanka
Author-email: piotr.maslanka@pfizer.com
License: UNKNOWN
Project-URL: Code, https://github.com/piotrmaslanka/pfizer-stratus-swagger
Project-URL: Issue tracker, https://github.com/piotrmaslanka/pfizer-stratus-swagger/issues
Keywords: swagger,pfizer,stratus,docs
Platform: UNKNOWN
Classifier: Programming Language :: Python
Classifier: Programming Language :: Python :: 3.8
Classifier: Programming Language :: Python :: 3.9
Classifier: Programming Language :: Python :: Implementation :: CPython
Classifier: Programming Language :: Python :: Implementation :: PyPy
Classifier: Operating System :: OS Independent
Classifier: Development Status :: 5 - Production/Stable
Classifier: License :: OSI Approved :: MIT License
Classifier: Topic :: Software Development :: Libraries
Requires-Python: !=3.5.*,!=3.6.*,!=3.7.*
Requires-Dist: pydantic (>=1.10.4)
Requires-Dist: pyyaml
Requires-Dist: satella
Requires-Dist: aws-lambda-powertools
Requires-Dist: openapi-schema-pydantic
